interactions/ext/tasks/__init__.py
interactions/ext/tasks/base.py
interactions/ext/tasks/tasks.py
interactions_tasks-1.0.0.dist-info/LICENSE
interactions_tasks-1.0.0.dist-info/METADATA
interactions_tasks-1.0.0.dist-info/WHEEL
interactions_tasks-1.0.0.dist-info/top_level.txt
interactions_tasks-1.0.0.dist-info/RECORD
