Metadata-Version: 2.1
Name: interactions-tasks
Version: 1.0.0
Summary: Add a task system to discord-py-interactions, similar to discord.ext.tasks
Home-page: https://github.com/Catalyst4222/interactions-tasks
Author: Catalyst4
Author-email: catalyst4222@gmail.com
License: MIT
Platform: UNKNOWN
Classifier: Programming Language :: Python :: 3
Classifier: Development Status :: 4 - Beta
Classifier: License :: OSI Approved :: MIT License
Classifier: Operating System :: OS Independent
License-File: LICENSE
